odoo/addons/pos_partner_no_create/README.rst
odoo/addons/pos_partner_no_create/__init__.py
odoo/addons/pos_partner_no_create/__manifest__.py
odoo/addons/pos_partner_no_create/i18n/pos_partner_no_create.pot
odoo/addons/pos_partner_no_create/readme/CONTRIBUTORS.rst
odoo/addons/pos_partner_no_create/readme/DESCRIPTION.rst
odoo/addons/pos_partner_no_create/static/description/icon.png
odoo/addons/pos_partner_no_create/static/description/index.html
odoo/addons/pos_partner_no_create/static/src/xml/templates.xml
odoo12_addon_pos_partner_no_create-12.0.2.0.2.dist-info/METADATA
odoo12_addon_pos_partner_no_create-12.0.2.0.2.dist-info/WHEEL
odoo12_addon_pos_partner_no_create-12.0.2.0.2.dist-info/top_level.txt
odoo12_addon_pos_partner_no_create-12.0.2.0.2.dist-info/RECORD
